Metadata-Version: 2.1
Name: pyeamxx
Version: 0.0.1
Summary: EAMxx wrapper
Author: SCREAM team
